fpdf_table/__init__.py
fpdf_table/main.py
fpdf_table-1.1.5.dist-info/LICENSE.md
fpdf_table-1.1.5.dist-info/METADATA
fpdf_table-1.1.5.dist-info/WHEEL
fpdf_table-1.1.5.dist-info/top_level.txt
fpdf_table-1.1.5.dist-info/RECORD
